obscureridge/__init__.py
obscureridge/__main__.py
obscureridge/chatbot.py
obscureridge/lichess.py
obscureridge/urllibutils.py
obscureridge/watchtourney.py
obscureridge-0.0.6.dist-info/LICENSE
obscureridge-0.0.6.dist-info/METADATA
obscureridge-0.0.6.dist-info/WHEEL
obscureridge-0.0.6.dist-info/entry_points.txt
obscureridge-0.0.6.dist-info/top_level.txt
obscureridge-0.0.6.dist-info/RECORD
