Metadata-Version: 2.1
Name: obscureridge
Version: 0.0.6
Summary: test project
Home-page: https://github.com/pythonflaskserverapps/obscureridge
Author: pythonflaskserverapps
Author-email: pythonflaskserverapps@gmail.com
License: MIT
Keywords: test project
Platform: UNKNOWN
Classifier: Development Status :: 5 - Production/Stable
Classifier: Intended Audience :: Developers
Classifier: Programming Language :: Python :: 3
Classifier: Programming Language :: Python :: 3.6
Requires-Python: >=3.6
